Metadata-Version: 1.0
Name: cleanenv
Version: 0.1.3
Summary: Clean environment using docker
Home-page: UNKNOWN
Author: Michael Peick
Author-email: python-cleanenv@n-pq.de
License: UNKNOWN
Platform: UNKNOWN
